LabelLib.cp39-win_amd64.pyd
LabelLib-2020.10.5.dist-info/LICENSE
LabelLib-2020.10.5.dist-info/METADATA
LabelLib-2020.10.5.dist-info/WHEEL
LabelLib-2020.10.5.dist-info/top_level.txt
LabelLib-2020.10.5.dist-info/RECORD
