Metadata-Version: 2.1
Name: LabelLib
Version: 2020.10.5
Summary: Python bindings for LabelLib
Home-page: https://github.com/Fluorescence-Tools/LabelLib
Author: Mykola Dimura
Author-email: mykola.dimura@gmail.com
License: MPL v2.0
Platform: UNKNOWN
Requires-Dist: numpy
